{"cameraMode":{"drawMode":0,"name":"Shaded","section":"Shading Mode"},"sceneLighting":false,"audioPlay":false,"sceneViewState":{"m_AlwaysRefresh":false,"showFog":true,"showSkybox":true,"showFlares":true,"showImageEffects":true,"showParticleSystems":true,"showVisualEffectGraphs":true,"m_FxEnabled":true},"in2DMode":false,"pivot":{"x":10.733673095703125,"y":-57.42210388183594,"z":-27.303470611572267},"rotation":{"x":-0.0648229569196701,"y":-0.8286023139953613,"z":0.5473989844322205,"w":-0.09814979881048203},"size":44.99575424194336,"orthographic":false}